[
  {
    "id": 1,
    "name": "Landing Page Básica",
    "description": "Diseño de landing page moderna y responsive, perfecta para presentar tu producto o servicio.",
    "price": 25000,
    "image": "/img/tienda-landing.png",
    "category": "web"
  },
  {
    "id": 2,
    "name": "Landing Page Premium",
    "description": "Landing page con animaciones, formularios integrados y diseño personalizado completo.",
    "price": 40000,
    "image": "/img/tienda-lading2.jpg",
    "category": "web"
  },
  {
    "id": 3,
    "name": "Diseño UX/UI",
    "description": "Diseño completo de interfaz de usuario y experiencia para tu aplicación web o móvil.",
    "price": 50000,
    "image": "/img/tienda-uxui.jpg",
    "category": "design"
  },
  {
    "id": 4,
    "name": "Branding Completo",
    "description": "Identidad visual completa: logo, paleta de colores, tipografías y manual de marca.",
    "price": 60000,
    "image": "/img/tienda-branding.png",
    "category": "branding"
  },
  {
    "id": 5,
    "name": "Ilustración Personalizada",
    "description": "Ilustraciones únicas hechas a mano para tu marca, proyectos o productos.",
    "price": 15000,
    "image": "/img/tienda-ilust.png",
    "category": "illustration"
  },
  {
    "id": 6,
    "name": "Diseño Editorial",
    "description": "Diseño de revista, catálogo o libro con maquetación profesional.",
    "price": 35000,
    "image": "/img/tienda-landing.png",
    "category": "editorial"
  },
  {
    "id": 7,
    "name": "Campaña Social Media",
    "description": "Diseño de contenido visual para redes sociales durante un mes.",
    "price": 30000,
    "image": "/img/tienda-landing.png",
    "category": "social"
  },
  {
    "id": 8,
    "name": "App Móvil UI",
    "description": "Diseño completo de interfaz para aplicación móvil iOS y Android.",
    "price": 70000,
    "image": "/img/tienda-landing.png",
    "category": "mobile"
  }
]
